setup.py
frasco_assets/__init__.py
frasco_assets/layout.html
frasco_assets.egg-info/PKG-INFO
frasco_assets.egg-info/SOURCES.txt
frasco_assets.egg-info/dependency_links.txt
frasco_assets.egg-info/not-zip-safe
frasco_assets.egg-info/requires.txt
frasco_assets.egg-info/top_level.txt