Metadata-Version: 1.0
Name: frasco-assets
Version: 0.1
Summary: Assets management using easywebassets for Frasco
Home-page: http://github.com/frascoweb/frasco-assets
Author: Maxime Bouroumeau-Fuseau
Author-email: maxime.bouroumeau@gmail.com
License: MIT
Platform: any
